hivemind_webchat/__init__.py
hivemind_webchat/__main__.py
hivemind_webchat/version.py
hivemind_webchat/webchat.py
hivemind_webchat/static/css/app.css
hivemind_webchat/static/css/bootstrap.min.css
hivemind_webchat/static/css/bootstrap.min.css.map
hivemind_webchat/static/css/font-awesome.css
hivemind_webchat/static/css/font-awesome.css.map
hivemind_webchat/static/css/todc-bootstrap.min.css
hivemind_webchat/static/css/todc-bootstrap.min.css.map
hivemind_webchat/static/fonts/FontAwesome.otf
hivemind_webchat/static/fonts/fontawesome-webfont.eot
hivemind_webchat/static/fonts/fontawesome-webfont.svg
hivemind_webchat/static/fonts/fontawesome-webfont.ttf
hivemind_webchat/static/fonts/fontawesome-webfont.woff
hivemind_webchat/static/fonts/fontawesome-webfont.woff2
hivemind_webchat/static/img/Logo2.png
hivemind_webchat/static/img/Logo2_.png
hivemind_webchat/static/img/blue_logo.png
hivemind_webchat/static/img/blue_logo_menu.png
hivemind_webchat/static/img/ovos-logo-512.png
hivemind_webchat/static/js/app.js
hivemind_webchat/static/js/jquery-3.2.1.min.js
hivemind_webchat/templates/index.html
hivemind_webchat-0.3.2a5.dist-info/LICENSE
hivemind_webchat-0.3.2a5.dist-info/METADATA
hivemind_webchat-0.3.2a5.dist-info/WHEEL
hivemind_webchat-0.3.2a5.dist-info/entry_points.txt
hivemind_webchat-0.3.2a5.dist-info/top_level.txt
hivemind_webchat-0.3.2a5.dist-info/RECORD
